MANIFEST.in
README.rst
setup.py
django_groundwork.egg-info/PKG-INFO
django_groundwork.egg-info/SOURCES.txt
django_groundwork.egg-info/dependency_links.txt
django_groundwork.egg-info/top_level.txt
groundwork/__init__.py
groundwork/urls.py
groundwork/static/foundation/css/foundation-icons.css
groundwork/static/foundation/css/foundation-icons.eot
groundwork/static/foundation/css/foundation-icons.svg
groundwork/static/foundation/css/foundation-icons.ttf
groundwork/static/foundation/css/foundation-icons.woff
groundwork/static/foundation/css/foundation.css
groundwork/static/foundation/css/foundation.min.css
groundwork/static/foundation/css/normalize.css
groundwork/static/foundation/js/foundation.min.js
groundwork/static/foundation/js/foundation/foundation.abide.js
groundwork/static/foundation/js/foundation/foundation.accordion.js
groundwork/static/foundation/js/foundation/foundation.alert.js
groundwork/static/foundation/js/foundation/foundation.clearing.js
groundwork/static/foundation/js/foundation/foundation.dropdown.js
groundwork/static/foundation/js/foundation/foundation.equalizer.js
groundwork/static/foundation/js/foundation/foundation.interchange.js
groundwork/static/foundation/js/foundation/foundation.joyride.js
groundwork/static/foundation/js/foundation/foundation.js
groundwork/static/foundation/js/foundation/foundation.magellan.js
groundwork/static/foundation/js/foundation/foundation.offcanvas.js
groundwork/static/foundation/js/foundation/foundation.orbit.js
groundwork/static/foundation/js/foundation/foundation.reveal.js
groundwork/static/foundation/js/foundation/foundation.slider.js
groundwork/static/foundation/js/foundation/foundation.tab.js
groundwork/static/foundation/js/foundation/foundation.tooltip.js
groundwork/static/foundation/js/foundation/foundation.topbar.js
groundwork/static/foundation/js/vendor/fastclick.js
groundwork/static/foundation/js/vendor/jquery.cookie.js
groundwork/static/foundation/js/vendor/jquery.js
groundwork/static/foundation/js/vendor/modernizr.js
groundwork/static/foundation/js/vendor/placeholder.js
groundwork/templates/groundwork/_paginator.html
