Metadata-Version: 1.1
Name: django-groundwork
Version: 0.2.5
Summary: A simple Django wrapper for Zurb Foundation
Home-page: https://github.com/dummerbd/django-groundwork
Author: Benjamin Dummer
Author-email: dummerbd@appstate.edu
License: BSD License
Platform: UNKNOWN
Classifier: Environment :: Web Environment
Classifier: Framework :: Django
Classifier: Intended Audience :: Developers
Classifier: Operating System :: OS Independent
Classifier: License :: OSI Approved :: BSD License
Classifier: Programming Language :: Python
Classifier: Programming Language :: Python :: 3.3
Classifier: Programming Language :: Python :: 3.4
Classifier: Topic :: Internet :: WWW/HTTP
Classifier: Topic :: Internet :: WWW/HTTP :: Dynamic Content
